{
  "kind": "ProblemDefinition",
  "id": "clean-water-problem",
  "version": "0.1.0",
  "title": "Classroom Clean Water System",
  "summary": "Design a classroom-scale system for exploring water movement and treatment tradeoffs without claiming potable water.",
  "mode": "education",
  "constraints": [
    {
      "id": "classroom-budget",
      "description": "Keep materials accessible for classrooms.",
      "unit": "USD",
      "max": 150
    }
  ],
  "metrics": [
    {
      "id": "treated-volume",
      "name": "Treated water volume",
      "unit": "L",
      "direction": "maximize",
      "baselineRefs": [
        "commercial-gravity-filter",
        "boil-chlorinate",
        "simple-sand-filter",
        "pump-cartridge-filter",
        "uv-treatment-concept"
      ]
    }
  ],
  "baselines": [
    {
      "id": "commercial-gravity-filter",
      "name": "Commercial gravity filter",
      "description": "Purchased classroom comparison baseline.",
      "confidence": {
        "level": "medium",
        "rationale": "Foundation example; not professional validation."
      },
      "sourceRefs": []
    },
    {
      "id": "boil-chlorinate",
      "name": "Boil chlorinate",
      "description": "Classroom discussion anchor for treatment tradeoffs; not a potable-water claim.",
      "confidence": {
        "level": "medium",
        "rationale": "Foundation example; not professional validation."
      },
      "sourceRefs": []
    },
    {
      "id": "simple-sand-filter",
      "name": "Simple sand filter",
      "description": "Classroom discussion anchor for filtration tradeoffs; not a potable-water claim.",
      "confidence": {
        "level": "medium",
        "rationale": "Foundation example; not professional validation."
      },
      "sourceRefs": []
    },
    {
      "id": "pump-cartridge-filter",
      "name": "Pump cartridge filter",
      "description": "Classroom discussion anchor for powered filtration tradeoffs; not a potable-water claim.",
      "confidence": {
        "level": "medium",
        "rationale": "Foundation example; not professional validation."
      },
      "sourceRefs": []
    },
    {
      "id": "uv-treatment-concept",
      "name": "UV treatment concept",
      "description": "Classroom discussion anchor for energy and treatment tradeoffs; not a potable-water claim.",
      "confidence": {
        "level": "medium",
        "rationale": "Foundation example; not professional validation."
      },
      "sourceRefs": []
    }
  ],
  "safetyNotes": [
    "No potable-water claim."
  ]
}
